{
  "cv_accuracy": 0.9627,
  "cv_f1": 0.9233,
  "cv_roc_auc": 0.9926,
  "oob_score": 0.9656,
  "optimal_threshold": 0.4598,
  "n_positives": 1369,
  "n_negatives": 4102,
  "feature_dim": 114,
  "sanity_check": {
    "valid": 0.9993261127642443,
    "wrong_room": 0.8927647389215647,
    "overloaded": 0.9258539824856064,
    "wrong_faculty": 0.6044968981996023
  },
  "top_features": [
    {
      "feature": "load_remaining",
      "importance": 0.181175
    },
    {
      "feature": "is_known_slot",
      "importance": 0.13441
    },
    {
      "feature": "fac_today_load_ratio",
      "importance": 0.101274
    },
    {
      "feature": "overload_severity",
      "importance": 0.043159
    },
    {
      "feature": "fac_course_affinity",
      "importance": 0.038513
    },
    {
      "feature": "rm_emb_19",
      "importance": 0.020159
    },
    {
      "feature": "rm_emb_18",
      "importance": 0.016481
    },
    {
      "feature": "rm_emb_21",
      "importance": 0.015574
    },
    {
      "feature": "rm_emb_8",
      "importance": 0.014365
    },
    {
      "feature": "near_weekly_cap",
      "importance": 0.01433
    },
    {
      "feature": "rm_emb_1",
      "importance": 0.013564
    },
    {
      "feature": "rm_emb_15",
      "importance": 0.012326
    },
    {
      "feature": "rm_emb_23",
      "importance": 0.011884
    },
    {
      "feature": "rm_emb_28",
      "importance": 0.010084
    },
    {
      "feature": "rm_emb_16",
      "importance": 0.009554
    }
  ]
}